mozark_sdk/__init__.py
mozark_sdk/client.py
mozark_sdk/device.py
mozark_sdk/executetest.py
mozark_sdk/file.py
mozark_sdk/project.py
mozark_sdk/schedule.py
mozark_sdk/test_analytics.py
mozark_sdk/tray.py
mozark_sdk/user.py
mozark_sdk-2.6.1.dist-info/LICENSE.txt
mozark_sdk-2.6.1.dist-info/METADATA
mozark_sdk-2.6.1.dist-info/WHEEL
mozark_sdk-2.6.1.dist-info/top_level.txt
mozark_sdk-2.6.1.dist-info/RECORD
