Metadata-Version: 2.1
Name: mozark-sdk
Version: 2.6.1
Summary: Automation test APIs
Home-page: https://mozark.ai
Author: Mozark
Author-email: mozark-aws-staging@mozark.ai
License: MIT
Keywords: MOZARK,AUTOMATION,EXPERIENCE
Platform: UNKNOWN
Classifier: Development Status :: 3 - Alpha
Classifier: Intended Audience :: Developers
Classifier: Topic :: Software Development :: Build Tools
Classifier: License :: OSI Approved :: MIT License
Classifier: Programming Language :: Python :: 3
Classifier: Programming Language :: Python :: 3.4
Classifier: Programming Language :: Python :: 3.5
Classifier: Programming Language :: Python :: 3.6
Classifier: Programming Language :: Python :: 3.7
Classifier: Programming Language :: Python :: 3.8
Classifier: Programming Language :: Python :: 3.9
Classifier: Programming Language :: Python :: 3.10
License-File: LICENSE.txt
Requires-Dist: configparser (==5.3.0)
Requires-Dist: requests (==2.28.1)
